owui_client/__init__.py
owui_client/client.py
owui_client/client_base.py
owui_client/shortcuts.py
owui_client/models/__init__.py
owui_client/models/audio.py
owui_client/models/auths.py
owui_client/models/channels.py
owui_client/models/chats.py
owui_client/models/configs.py
owui_client/models/evaluations.py
owui_client/models/feedbacks.py
owui_client/models/files.py
owui_client/models/folders.py
owui_client/models/functions.py
owui_client/models/groups.py
owui_client/models/images.py
owui_client/models/knowledge.py
owui_client/models/memories.py
owui_client/models/messages.py
owui_client/models/models.py
owui_client/models/notes.py
owui_client/models/oauth_sessions.py
owui_client/models/ollama.py
owui_client/models/openai.py
owui_client/models/pipelines.py
owui_client/models/prompts.py
owui_client/models/retrieval.py
owui_client/models/root.py
owui_client/models/tags.py
owui_client/models/tasks.py
owui_client/models/tools.py
owui_client/models/users.py
owui_client/models/utils.py
owui_client/routers/__init__.py
owui_client/routers/audio.py
owui_client/routers/auths.py
owui_client/routers/channels.py
owui_client/routers/chats.py
owui_client/routers/configs.py
owui_client/routers/evaluations.py
owui_client/routers/files.py
owui_client/routers/folders.py
owui_client/routers/functions.py
owui_client/routers/groups.py
owui_client/routers/images.py
owui_client/routers/knowledge.py
owui_client/routers/memories.py
owui_client/routers/models.py
owui_client/routers/notes.py
owui_client/routers/ollama.py
owui_client/routers/openai.py
owui_client/routers/pipelines.py
owui_client/routers/prompts.py
owui_client/routers/retrieval.py
owui_client/routers/root.py
owui_client/routers/tasks.py
owui_client/routers/tools.py
owui_client/routers/users.py
owui_client/routers/utils.py
owui_client-1.3.0.dist-info/METADATA
owui_client-1.3.0.dist-info/WHEEL
owui_client-1.3.0.dist-info/licenses/LICENSE
owui_client-1.3.0.dist-info/RECORD
