Metadata-Version: 2.4
Name: owui-client
Version: 1.3.0
Summary: Unofficial async Python client for the complete Open WebUI API.
Project-URL: Author, https://willhogben.com
Project-URL: Repository, https://github.com/whogben/owui_client
Project-URL: Issues, https://github.com/whogben/owui_client/issues
Project-URL: Documentation, https://whogben.github.io/owui_client/
Author-email: William Hogben <whogben@gmail.com>
License: MIT
License-File: LICENSE
Keywords: api,client,open-webui
Requires-Python: >=3.10
Requires-Dist: httpx>=0.27.0
Requires-Dist: pydantic>=2.0.0
Provides-Extra: dev
Requires-Dist: pytest; extra == 'dev'
Requires-Dist: pytest-asyncio; extra == 'dev'
